{
  "name": "recurrence",
  "base": "PersistedModel",
  "idInjection": true,
  "options": {
    "validateUpsert": true
  },
  "properties": {
    "start_date": {
      "type": "date",
      "required": true
    },
    "end_date": {
      "type": "date",
      "required": true
    }
  },
  "validations": [],
  "relations": {
    "assignments": {
      "type": "hasMany",
      "model": "doctor_assignment",
      "foreignKey": "rec_id"
    },
    "appointment": {
      "type": "hasMany",
      "model": "appointment",
      "foreignKey": "rec_id"
    },
    "specialityAssignments": {
      "type": "hasMany",
      "model": "speciality_assignment",
      "foreignKey": "rec_id"
    }
  },
  "acls": [],
  "methods": {}
}
